[
  {
    "inputs": [
      {
        "internalType": "address",
        "name": "_eigenStrategy",
        "type": "address"
      },
      {
        "internalType": "address",
        "name": "_delegationManager",
        "type": "address"
      }
    ],
    "stateMutability": "nonpayable",
    "type": "constructor"
  },
  {
    "anonymous": false,
    "inputs": [
      {
        "indexed": false,
        "internalType": "uint256",
        "name": "amount",
        "type": "uint256"
      },
      {
        "indexed": false,
        "internalType": "uint256",
        "name": "timestamp",
        "type": "uint256"
      }
    ],
    "name": "ArtistWithdrawal",
    "type": "event"
  },
  {
    "anonymous": false,
    "inputs": [
      {
        "indexed": false,
        "internalType": "uint256",
        "name": "artistAmount",
        "type": "uint256"
      },
      {
        "indexed": false,
        "internalType": "uint256",
        "name": "stakersAmount",
        "type": "uint256"
      },
      {
        "indexed": false,
        "internalType": "uint256",
        "name": "monthIndex",
        "type": "uint256"
      }
    ],
    "name": "RoyaltiesDistributed",
    "type": "event"
  },
  {
    "anonymous": false,
    "inputs": [
      {
        "indexed": true,
        "internalType": "address",
        "name": "staker",
        "type": "address"
      },
      {
        "indexed": false,
        "internalType": "uint256",
        "name": "amount",
        "type": "uint256"
      }
    ],
    "name": "Staked",
    "type": "event"
  },
  {
    "anonymous": false,
    "inputs": [
      {
        "indexed": false,
        "internalType": "uint256",
        "name": "newPrice",
        "type": "uint256"
      },
      {
        "indexed": false,
        "internalType": "uint256",
        "name": "streamCount",
        "type": "uint256"
      }
    ],
    "name": "TokenPriceUpdated",
    "type": "event"
  },
  {
    "anonymous": false,
    "inputs": [
      {
        "indexed": true,
        "internalType": "address",
        "name": "staker",
        "type": "address"
      },
      {
        "indexed": false,
        "internalType": "uint256",
        "name": "amount",
        "type": "uint256"
      }
    ],
    "name": "Unstaked",
    "type": "event"
  },
  {
    "inputs": [],
    "name": "artistWithdraw",
    "outputs": [],
    "stateMutability": "nonpayable",
    "type": "function"
  },
  {
    "inputs": [],
    "name": "artistWithdrawableBalance",
    "outputs": [
      {
        "internalType": "uint256",
        "name": "",
        "type": "uint256"
      }
    ],
    "stateMutability": "view",
    "type": "function"
  },
  {
    "inputs": [
      {
        "internalType": "uint256",
        "name": "streamCount",
        "type": "uint256"
      }
    ],
    "name": "depositMonthlyRoyalties",
    "outputs": [],
    "stateMutability": "payable",
    "type": "function"
  },
  {
    "inputs": [],
    "name": "eigenStrategy",
    "outputs": [
      {
        "internalType": "contract IStrategy",
        "name": "",
        "type": "address"
      }
    ],
    "stateMutability": "view",
    "type": "function"
  },
  {
    "inputs": [],
    "name": "getCurrentPrice",
    "outputs": [
      {
        "internalType": "uint256",
        "name": "",
        "type": "uint256"
      }
    ],
    "stateMutability": "view",
    "type": "function"
  },
  {
    "inputs": [
      {
        "internalType": "address",
        "name": "account",
        "type": "address"
      }
    ],
    "name": "getStakedBalance",
    "outputs": [
      {
        "internalType": "uint256",
        "name": "",
        "type": "uint256"
      }
    ],
    "stateMutability": "view",
    "type": "function"
  },
  {
    "inputs": [],
    "name": "getStakersCount",
    "outputs": [
      {
        "internalType": "uint256",
        "name": "",
        "type": "uint256"
      }
    ],
    "stateMutability": "view",
    "type": "function"
  },
  {
    "inputs": [
      {
        "internalType": "uint256",
        "name": "amount",
        "type": "uint256"
      }
    ],
    "name": "stake",
    "outputs": [],
    "stateMutability": "nonpayable",
    "type": "function"
  },
  {
    "inputs": [],
    "name": "totalSupply",
    "outputs": [
      {
        "internalType": "uint256",
        "name": "",
        "type": "uint256"
      }
    ],
    "stateMutability": "view",
    "type": "function"
  },
  {
    "inputs": [
      {
        "internalType": "uint256",
        "name": "amount",
        "type": "uint256"
      }
    ],
    "name": "unstake",
    "outputs": [],
    "stateMutability": "nonpayable",
    "type": "function"
  }
] 